setup.py
kickscraper/__init__.py
kickscraper.egg-info/PKG-INFO
kickscraper.egg-info/SOURCES.txt
kickscraper.egg-info/dependency_links.txt
kickscraper.egg-info/pbr.json
kickscraper.egg-info/requires.txt
kickscraper.egg-info/top_level.txt