Metadata-Version: 1.1
Name: kickscraper
Version: 0.1.6
Summary: A scraper for Crowdfunding platform projects like kickstarter
Home-page: https://github.com/argaen/kickscraper
Author: argaen
Author-email: manu.mirandad@gmail.com
License: MIT
Keywords: kickstarter api crowdfunding projects
Platform: UNKNOWN
Classifier: Development Status :: 4 - Beta
Classifier: Intended Audience :: Developers
Classifier: License :: OSI Approved :: MIT License
Classifier: Programming Language :: Python :: 3
Classifier: Programming Language :: Python :: 2
